odoo/addons/account_invoice_force_number/README.rst
odoo/addons/account_invoice_force_number/__init__.py
odoo/addons/account_invoice_force_number/__manifest__.py
odoo/addons/account_invoice_force_number/i18n/account_invoice_force_number.pot
odoo/addons/account_invoice_force_number/i18n/ar.po
odoo/addons/account_invoice_force_number/i18n/bg.po
odoo/addons/account_invoice_force_number/i18n/bs.po
odoo/addons/account_invoice_force_number/i18n/ca.po
odoo/addons/account_invoice_force_number/i18n/cs.po
odoo/addons/account_invoice_force_number/i18n/de.po
odoo/addons/account_invoice_force_number/i18n/el_GR.po
odoo/addons/account_invoice_force_number/i18n/en_GB.po
odoo/addons/account_invoice_force_number/i18n/es.po
odoo/addons/account_invoice_force_number/i18n/es_CR.po
odoo/addons/account_invoice_force_number/i18n/es_EC.po
odoo/addons/account_invoice_force_number/i18n/es_MX.po
odoo/addons/account_invoice_force_number/i18n/et.po
odoo/addons/account_invoice_force_number/i18n/fi.po
odoo/addons/account_invoice_force_number/i18n/fr.po
odoo/addons/account_invoice_force_number/i18n/fr_CH.po
odoo/addons/account_invoice_force_number/i18n/gl.po
odoo/addons/account_invoice_force_number/i18n/hr.po
odoo/addons/account_invoice_force_number/i18n/hr_HR.po
odoo/addons/account_invoice_force_number/i18n/id.po
odoo/addons/account_invoice_force_number/i18n/it.po
odoo/addons/account_invoice_force_number/i18n/ja.po
odoo/addons/account_invoice_force_number/i18n/lt.po
odoo/addons/account_invoice_force_number/i18n/mk.po
odoo/addons/account_invoice_force_number/i18n/mn.po
odoo/addons/account_invoice_force_number/i18n/nb_NO.po
odoo/addons/account_invoice_force_number/i18n/nl.po
odoo/addons/account_invoice_force_number/i18n/nl_BE.po
odoo/addons/account_invoice_force_number/i18n/pl.po
odoo/addons/account_invoice_force_number/i18n/pt.po
odoo/addons/account_invoice_force_number/i18n/pt_BR.po
odoo/addons/account_invoice_force_number/i18n/pt_PT.po
odoo/addons/account_invoice_force_number/i18n/ro.po
odoo13_addon_account_invoice_force_number-13.0.1.0.1.dev9.dist-info/METADATA
odoo13_addon_account_invoice_force_number-13.0.1.0.1.dev9.dist-info/WHEEL
odoo13_addon_account_invoice_force_number-13.0.1.0.1.dev9.dist-info/top_level.txt
odoo13_addon_account_invoice_force_number-13.0.1.0.1.dev9.dist-info/RECORD
