Metadata-Version: 2.1
Name: odoo13-addon-account-invoice-force-number
Version: 13.0.1.0.1.dev9
Summary: Allows to force invoice numbering on specific invoices
Home-page: https://github.com/OCA/account-invoicing
Author: Agile Business Group, Odoo Community Association (OCA)
Author-email: support@odoo-community.org
License: AGPL-3
Platform: UNKNOWN
Classifier: Programming Language :: Python
Classifier: Framework :: Odoo
Classifier: Framework :: Odoo :: 13.0
Classifier: License :: OSI Approved :: GNU Affero General Public License v3
Requires-Python: >=3.5
Requires-Dist: odoo <13.1dev,>=13.0a
